{"get": "players", "parameters": {"id": "2932", "league": "1", "season": "2022"}, "errors": [], "results": 1, "paging": {"current": 1, "total": 1}, "response": [{"player": {"id": 2932, "name": "J. Pickford", "firstname": "Jordan Lee", "lastname": "Pickford", "age": 31, "birth": {"date": "1994-03-07", "place": "Washington", "country": "England"}, "nationality": "England", "height": "185", "weight": "82", "injured": false, "photo": "https://media.api-sports.io/football/players/2932.png"}, "statistics": [{"team": {"id": 10, "name": "England", "logo": "https://media.api-sports.io/football/teams/10.png"}, "league": {"id": 1, "name": "World Cup", "country": "World", "logo": "https://media.api-sports.io/football/leagues/1.png", "flag": null, "season": 2022}, "games": {"appearences": 5, "lineups": 5, "minutes": 450, "number": 1, "position": "Goalkeeper", "rating": "6.96", "captain": false}, "substitutes": {"in": 0, "out": 0, "bench": 0}, "shots": {"total": null, "on": null}, "goals": {"total": 0, "conceded": 4, "assists": 0, "saves": 7}, "passes": {"total": 145, "key": null, "accuracy": 77}, "tackles": {"total": null, "blocks": null, "interceptions": null}, "duels": {"total": null, "won": null}, "dribbles": {"attempts": null, "success": null, "past": null}, "fouls": {"drawn": null, "committed": null}, "cards": {"yellow": 0, "yellowred": 0, "red": 0}, "penalty": {"won": null, "commited": null, "scored": 0, "missed": 0, "saved": 0}}]}]}